mopidy_subidy/__init__.py
mopidy_subidy/backend.py
mopidy_subidy/ext.conf
mopidy_subidy/library.py
mopidy_subidy/playback.py
mopidy_subidy/playlists.py
mopidy_subidy/subsonic_api.py
mopidy_subidy/uri.py
Mopidy_Subidy-1.1.0.dist-info/LICENSE
Mopidy_Subidy-1.1.0.dist-info/METADATA
Mopidy_Subidy-1.1.0.dist-info/WHEEL
Mopidy_Subidy-1.1.0.dist-info/entry_points.txt
Mopidy_Subidy-1.1.0.dist-info/top_level.txt
Mopidy_Subidy-1.1.0.dist-info/RECORD
